molx/__init__.py
molx/version.py
molx/dataset/__init__.py
molx/dataset/molecule3d.py
molx/dataset/utils.py
molx/model/__init__.py
molx/model/deepergcn_dagnn.py
molx/model/schnet.py
molx/model/schnet_2d.py
molx/mol3d/__init__.py
molx/mol3d/train_eval.py
molx/mol3d/transform.py
molx/mol3d/utils.py
molx/proppred/__init__.py
molx/proppred/reg_trainer.py
moleculex-0.0.3.dist-info/LICENSE
moleculex-0.0.3.dist-info/METADATA
moleculex-0.0.3.dist-info/WHEEL
moleculex-0.0.3.dist-info/top_level.txt
moleculex-0.0.3.dist-info/RECORD
