Metadata-Version: 2.1
Name: moleculex
Version: 0.0.3
Summary: MoleculeX: a new and rapidly growing suite of machine     learning methods and software tools for molecule exploration
Home-page: https://github.com/divelab/MoleculeX
Author: DIVE Lab@TAMU
Author-email: sji@tamu.edu
Maintainer: DIVE Lab@TAMU
License: GPLv3
Platform: UNKNOWN
Classifier: Programming Language :: Python :: 3
Classifier: License :: OSI Approved :: GNU General Public License v3 (GPLv3)
Classifier: Operating System :: OS Independent
Requires-Python: >=3.6
License-File: LICENSE
Requires-Dist: scipy
Requires-Dist: cilog
Requires-Dist: typed-argument-parser (==1.5.4)
Requires-Dist: captum (==0.2.0)
Requires-Dist: shap
Requires-Dist: IPython
Requires-Dist: tqdm
Requires-Dist: rdkit-pypi
Requires-Dist: pandas
